yeastarapi/_Connection.py
yeastarapi/_Messages.py
yeastarapi/_System.py
yeastarapi/__init__.py
yeastarAPI-0.1.5.dist-info/LICENSE
yeastarAPI-0.1.5.dist-info/METADATA
yeastarAPI-0.1.5.dist-info/WHEEL
yeastarAPI-0.1.5.dist-info/top_level.txt
yeastarAPI-0.1.5.dist-info/RECORD
